<?xml version="1.0" encoding="utf-8" ?>
<dwsync>
<file name="knop boven leeg up.jpg" server="users.telenet.be" local="128128999800000000" remote="132690051600000000" Dst="2" />
<file name="sknop boven up krant.jpg" server="users.telenet.be" local="127437698400000000" remote="132690051600000000" Dst="2" />
<file name="sknop onder down gastenboek.jpg" server="users.telenet.be" local="127437698400000000" remote="132690051600000000" Dst="2" />
<file name="sknop boven down krant.jpg" server="users.telenet.be" local="127437698400000000" remote="132690051600000000" Dst="2" />
<file name="navigatiebar.jpg" server="users.telenet.be" local="128139687600000000" remote="132690051600000000" Dst="2" />
<file name="sknop onder down links.jpg" server="users.telenet.be" local="127437698400000000" remote="132690051600000000" Dst="2" />
<file name="sknop onder down speelplaats.jpg" server="users.telenet.be" local="127437698400000000" remote="132690051600000000" Dst="2" />
<file name="sknop onder up gastenboek.jpg" server="users.telenet.be" local="127437698400000000" remote="132690051600000000" Dst="2" />
<file name="sknop onder up links.jpg" server="users.telenet.be" local="127437698400000000" remote="132690051600000000" Dst="2" />
<file name="sknop onder up speelplaats.jpg" server="users.telenet.be" local="127437698400000000" remote="132690051600000000" Dst="2" />
<file name="zedenleer voorblad.jpg" server="users.telenet.be" local="128128988920000000" remote="132690051600000000" Dst="2" />
</dwsync>