<?xml version="1.0" encoding="utf-8" ?>
<dwsync>
<file name="1975 (Small).jpg" server="users.telenet.be" local="128129091000000000" remote="132690051600000000" Dst="2" />
<file name="1980 (Small).jpg" server="users.telenet.be" local="128129091000000000" remote="132690051600000000" Dst="2" />
<file name="1985 (Small).jpg" server="users.telenet.be" local="128129091000000000" remote="132690051600000000" Dst="2" />
<file name="1990 (Small).jpg" server="users.telenet.be" local="128129091000000000" remote="132690051600000000" Dst="2" />
<file name="1995 (Small).jpg" server="users.telenet.be" local="128129091000000000" remote="132690051600000000" Dst="2" />
<file name="2000 (Small).jpg" server="users.telenet.be" local="128129091000000000" remote="132690051600000000" Dst="2" />
<file name="2005 (Small).jpg" server="users.telenet.be" local="128129091600000000" remote="132690051600000000" Dst="2" />
<file name="bord1975kopie (Small).jpg" server="users.telenet.be" local="128129091600000000" remote="132690051600000000" Dst="2" />
<file name="allesverandert.htm" server="users.telenet.be" local="132689996358470219" remote="132690051600000000" Dst="2" />
<file name="bord1995 (Small).jpg" server="users.telenet.be" local="128129091600000000" remote="132690051600000000" Dst="2" />
</dwsync>